{
  "call_id": "BATCH_ID_150",
  "intent": "reschedule_cancel",
  "is_gap": false,
  "ended_in_transfer": false,
  "turns": [
    {
      "speaker": "caller",
      "text": "Uh, hi. I booked an appointment last week online and I want to, uh, change the timing. Not the date, just the time."
    },
    {
      "speaker": "agent",
      "text": "Sure, that's easy to do. Name and number please?"
    },
    {
      "speaker": "caller",
      "text": "Shweta Bhatt. 9823115566."
    },
    {
      "speaker": "agent",
      "text": "I see your appointment with Dr. Kiran Bhosale in neurology this Wednesday at 9 AM. What time would you prefer?"
    },
    {
      "speaker": "caller",
      "text": "Can I get something after 11? I have a school drop to manage in the morning."
    },
    {
      "speaker": "agent",
      "text": "11:30 AM on Wednesday works for Dr. Bhosale. Shall I update that?"
    },
    {
      "speaker": "caller",
      "text": "Yes please."
    },
    {
      "speaker": "agent",
      "text": "Updated! Wednesday appointment now at 11:30 AM. See you then, Ms. Bhatt."
    },
    {
      "speaker": "caller",
      "text": "Perfect, thanks so much."
    }
  ]
}