{
  "call_id": "BATCH_ID_116",
  "intent": "book_appointment",
  "is_gap": false,
  "ended_in_transfer": false,
  "turns": [
    {
      "speaker": "caller",
      "text": "Hello. Mujhe ek haematologist se milna hai. Mere blood reports mein kuch abnormal aaya hai — platelet count related."
    },
    {
      "speaker": "agent",
      "text": "Zaroor, yeh important hai. Aapka naam aur number?"
    },
    {
      "speaker": "caller",
      "text": "Swapnil Ghate. 9765234890."
    },
    {
      "speaker": "agent",
      "text": "Shukriya Swapnil ji. Humare haematologist Dr. Arun Pendse hain. Unka clinic schedule Mangalvaar aur Shukravaar hai. Kaunsa din theek hai?"
    },
    {
      "speaker": "caller",
      "text": "Shukravaar — kal — agar slot ho toh urgent basis pe."
    },
    {
      "speaker": "agent",
      "text": "Kal Shukravaar 11 AM ka slot hai. Aur abnormal reports ke case mein hum ise priority mein mark kar lete hain. Aap apni reports saath laana zaroor."
    },
    {
      "speaker": "caller",
      "text": "Haan, sab reports hain mere paas. Book kar dijiye please."
    },
    {
      "speaker": "agent",
      "text": "Done! Swapnil Ghate, kal Shukravaar 11 AM, Dr. Arun Pendse. Jaldi se report milegi aapko."
    }
  ]
}